<?xml version="1.0" encoding="UTF-8"?>
<SlimOTA xmlns:xsi="http://www.w3.org/2001/XMLSchema-instance" xsi:noNamespaceSchemaLocation="ota.xsd">
    <Official>
        <cheeseburger>
            <Filename>9.1.3-20180713-OFFICIAL-cheeseburger.zip</Filename>
            <RomUrl
                id="rom"
                title="LiquidRemix"
                description="Download latest build for cheeseburger">https://www.androidfilehost.com/?fid=5862345805528047585</RomUrl>
            <ChangelogUrl
                id="changelog"
                title="Changelog"
                description="Click here to view latest changes">https://del.dog/ocejevetin.coffeescript</ChangelogUrl>
            <OpenGappsUrl
            	id="open_gapps"
            	title="OpenGApps"
            	description="Download latest OpenGApps for Android Oreo">https://opengapps.org</OpenGappsUrl>
        </cheeseburger>
        <dumpling>
            <Filename>9.1.3-20180713-OFFICIAL-dumpling.zip</Filename>
            <RomUrl
                id="rom"
                title="LiquidRemix"
                description="Download latest build for dumpling">https://www.androidfilehost.com/?fid=5862345805528047586</RomUrl>
            <ChangelogUrl
                id="changelog"
                title="Changelog"
                description="Click here to view latest changes">https://del.dog/ocejevetin.coffeescript</ChangelogUrl>
            <OpenGappsUrl
            	id="open_gapps"
            	title="OpenGApps"
            	description="Download latest OpenGApps for Android Oreo">https://opengapps.org</OpenGappsUrl>
        </dumpling>
    </Official>
    <Weekly>
        <cheeseburger>
            <Filename>9.1.4-20180803-WEEKLY-cheeseburger.zip</Filename>
            <RomUrl
                id="rom"
                title="LiquidRemix"
                description="Download latest build for cheeseburger">https://www.androidfilehost.com/?fid=5862345805528064906</RomUrl>
            <ChangelogUrl
                id="changelog"
                title="Changelog"
                description="Click here to view latest changes">https://del.dog/uticobonec.sh</ChangelogUrl>
            <OpenGappsUrl
            	id="open_gapps"
            	title="OpenGApps"
            	description="Download latest OpenGApps for Android Oreo">https://opengapps.org</OpenGappsUrl>
        </cheeseburger>
        <dumpling>
            <Filename>9.1.4-20180803-WEEKLY-dumpling.zip</Filename>
            <RomUrl
                id="rom"
                title="LiquidRemix"
                description="Download latest build for dumpling">https://www.androidfilehost.com/?fid=5862345805528064910</RomUrl>
            <ChangelogUrl
                id="changelog"
                title="Changelog"
                description="Click here to view latest changes">https://del.dog/uticobonec.sh</ChangelogUrl>
            <OpenGappsUrl
            	id="open_gapps"
            	title="OpenGApps"
            	description="Download latest OpenGApps for Android Oreo">https://opengapps.org</OpenGappsUrl>
        </dumpling>
    </Weekly>
</SlimOTA>
